govqa/__init__.py
govqa/base.py
govqa/input_types.py
govqa-1.0.1.dist-info/METADATA
govqa-1.0.1.dist-info/WHEEL
govqa-1.0.1.dist-info/top_level.txt
govqa-1.0.1.dist-info/RECORD
